shipyard_microsoft_sharepoint/__init__.py
shipyard_microsoft_sharepoint/cli/authtest.py
shipyard_microsoft_sharepoint/cli/download.py
shipyard_microsoft_sharepoint/cli/move.py
shipyard_microsoft_sharepoint/cli/remove.py
shipyard_microsoft_sharepoint/cli/upload.py
shipyard_microsoft_sharepoint/errs.py
shipyard_microsoft_sharepoint/sharepoint.py
shipyard_microsoft_sharepoint-0.1.0.dist-info/METADATA
shipyard_microsoft_sharepoint-0.1.0.dist-info/WHEEL
shipyard_microsoft_sharepoint-0.1.0.dist-info/RECORD
