Metadata-Version: 2.1
Name: shipyard-microsoft-sharepoint
Version: 0.1.0
Summary: A local client for working with Microsoft SharePoint
Author: wrp801
Author-email: wespoulsen@gmail.com
Requires-Python: >=3.9,<4.0
Classifier: Programming Language :: Python :: 3
Classifier: Programming Language :: Python :: 3.9
Classifier: Programming Language :: Python :: 3.10
Classifier: Programming Language :: Python :: 3.11
Requires-Dist: msal (>=1.30.0,<2.0.0)
Requires-Dist: requests (==2.31)
Requires-Dist: shipyard-bp-utils (>=1.2.1,<2.0.0)
Requires-Dist: shipyard-templates (>=0.9.0,<0.10.0)
